Metadata-Version: 1.2
Name: pygo-main
Version: 1.4
Summary: python project sdk
Home-page: http://pygo2.cn
Author: pygo
Author-email: gaoming971366@163.com
License: MIT Licence
Keywords: main,pygo,python2
Platform: any
Requires-Python: >=2.7
